{
  "wublockchainenglish": {
    "consecutive_zero": 0,
    "alerted": false,
    "last_ok_run": "2026-07-20T16:51:40.505333+00:00"
  },
  "tokenpost": {
    "consecutive_zero": 0,
    "alerted": false,
    "last_ok_run": "2026-07-20T16:51:40.505351+00:00"
  },
  "blockmedia": {
    "consecutive_zero": 0,
    "alerted": false,
    "last_ok_run": "2026-07-20T16:51:40.505355+00:00"
  },
  "decenter": {
    "consecutive_zero": 0,
    "alerted": false,
    "last_ok_run": "2026-07-20T16:51:40.505358+00:00"
  },
  "cointelegraph": {
    "consecutive_zero": 0,
    "alerted": false,
    "last_ok_run": "2026-07-20T16:51:40.505360+00:00"
  },
  "decrypt": {
    "consecutive_zero": 0,
    "alerted": false,
    "last_ok_run": "2026-07-20T16:51:40.505362+00:00"
  },
  "coindesk": {
    "consecutive_zero": 0,
    "alerted": false,
    "last_ok_run": "2026-07-20T16:51:40.505363+00:00"
  },
  "blockworks": {
    "consecutive_zero": 0,
    "alerted": false,
    "last_ok_run": "2026-07-20T16:51:40.505365+00:00"
  },
  "coingecko_news": {
    "consecutive_zero": 0,
    "alerted": false,
    "last_ok_run": "2026-07-20T16:51:40.505367+00:00"
  },
  "coinness": {
    "consecutive_zero": 3,
    "alerted": true
  },
  "xangle": {
    "consecutive_zero": 2,
    "alerted": false
  },
  "bloomingbit": {
    "consecutive_zero": 2,
    "alerted": false
  },
  "coinmarketcap_community": {
    "consecutive_zero": 0,
    "alerted": false,
    "last_ok_run": "2026-07-20T16:51:40.505369+00:00"
  }
}